[
  {
    "imageType": "external",
    "sourceRepo": "registry.access.redhat.com",
    "sourceNamespace": "ubi9",
    "sourceImage": "ubi-micro",
    "destStage": "edge",
    "destNamespace": "build-images",
    "destImage": "ubi9-micro",
    "tag": "9.5-1731519709",
    "updatePackages": []
  },
  {
    "imageType": "external",
    "sourceRepo": "registry.access.redhat.com",
    "sourceNamespace": "ubi9",
    "sourceImage": "ubi",
    "destStage": "edge",
    "destNamespace": "build-images",
    "destImage": "ubi9",
    "tag": "9.5-1731517889",
    "updatePackages": []
  },
  {
    "imageType": "external",
    "sourceRepo": "registry.access.redhat.com",
    "sourceNamespace": "ubi9",
    "sourceImage": "ubi-minimal",
    "destStage": "edge",
    "destNamespace": "build-images",
    "destImage": "ubi9-minimal",
    "tag": "9.5-1731593028",
    "updatePackages": []
  },
  {
    "imageType": "node",
    "sourceImage": "ubi9-minimal",
    "sourceTag": "9.5-1731593028",
    "destImage": "node-v18-ubi9-minimal",
    "nodeVersion": "18.20.5"
  },
  {
    "imageType": "node",
    "sourceImage": "ubi9-minimal",
    "sourceTag": "9.5-1731593028",
    "destImage": "node-v20-ubi9-minimal",
    "nodeVersion": "20.18.0"
  }
]
